captchabusters/__init__.py
captchabusters-1.0.0.dist-info/METADATA
captchabusters-1.0.0.dist-info/WHEEL
captchabusters-1.0.0.dist-info/top_level.txt
captchabusters-1.0.0.dist-info/RECORD
