Metadata-Version: 2.1
Name: captchabusters
Version: 1.0.0
Summary: Python package for interacting with the CaptchaBusters API
Home-page: https://github.com/yourusername/captchabusters-python
Author: Its3rr0rsWRLD
Requires-Dist: requests
